<suitelet scriptid="customscript_ba_vb_emailhandler_sl">
  <description></description>
  <isinactive>F</isinactive>
  <name>BA | Vendor Bill Email Handler SL</name>
  <notifyadmins>F</notifyadmins>
  <notifyemails></notifyemails>
  <notifyowner>T</notifyowner>
  <notifyuser>F</notifyuser>
  <scriptfile>[/SuiteScripts/BA_Bill_ApprovalHandler_SL.js]</scriptfile>
  <scriptcustomfields>
    <scriptcustomfield scriptid="custscript_second_approver">
      <accesslevel>2</accesslevel>
      <applyformatting>F</applyformatting>
      <checkspelling>F</checkspelling>
      <defaultchecked>F</defaultchecked>
      <defaultselection></defaultselection>
      <defaultvalue></defaultvalue>
      <description></description>
      <displayheight></displayheight>
      <displaytype>NORMAL</displaytype>
      <displaywidth></displaywidth>
      <dynamicdefault></dynamicdefault>
      <fieldtype>SELECT</fieldtype>
      <help></help>
      <isformula>F</isformula>
      <ismandatory>F</ismandatory>
      <label>Second Approver</label>
      <linktext></linktext>
      <maxlength></maxlength>
      <maxvalue></maxvalue>
      <minvalue></minvalue>
      <onparentdelete>SET_NULL</onparentdelete>
      <searchlevel>2</searchlevel>
      <selectrecordtype>-4</selectrecordtype>
      <setting></setting>
      <storevalue>T</storevalue>
    </scriptcustomfield>
    <scriptcustomfield scriptid="custscript_super_approver">
      <accesslevel>2</accesslevel>
      <applyformatting>F</applyformatting>
      <checkspelling>F</checkspelling>
      <defaultchecked>F</defaultchecked>
      <defaultselection></defaultselection>
      <defaultvalue></defaultvalue>
      <description></description>
      <displayheight></displayheight>
      <displaytype>NORMAL</displaytype>
      <displaywidth></displaywidth>
      <dynamicdefault></dynamicdefault>
      <fieldtype>SELECT</fieldtype>
      <help></help>
      <isformula>F</isformula>
      <ismandatory>F</ismandatory>
      <label>Super Approver</label>
      <linktext></linktext>
      <maxlength></maxlength>
      <maxvalue></maxvalue>
      <minvalue></minvalue>
      <onparentdelete>SET_NULL</onparentdelete>
      <searchlevel>2</searchlevel>
      <selectrecordtype>-4</selectrecordtype>
      <setting></setting>
      <storevalue>T</storevalue>
    </scriptcustomfield>
  </scriptcustomfields>
  <scriptdeployments>
    <scriptdeployment scriptid="customdeploy1">
      <allemployees>F</allemployees>
      <allpartners>F</allpartners>
      <allroles>T</allroles>
      <audslctrole></audslctrole>
      <custscript_second_approver>[ACCOUNT_SPECIFIC_VALUE]</custscript_second_approver>
      <custscript_super_approver>[ACCOUNT_SPECIFIC_VALUE]</custscript_super_approver>
      <eventtype></eventtype>
      <isdeployed>T</isdeployed>
      <isonline>T</isonline>
      <loglevel>DEBUG</loglevel>
      <runasrole>ADMINISTRATOR</runasrole>
      <status>RELEASED</status>
      <title>BA | Vendor Bill Email Handler SL</title>
    </scriptdeployment>
  </scriptdeployments>
</suitelet>